[
    {
        "ClassRegistration": {
            "AfternoonPeriod": [
                {
                    "ClassName1ThirdPeriod": "Corning Glass Adventure", 
                    "ClassName2ThirdPeriod": null, 
                    "ItemNumber": 1, 
                    "Leader": "Donna Miller-Small", 
                    "Leader2": ""
                }
            ], 
            "AfternoonPeriod_Minimum": 0, 
            "MorningFirstPeriod": [
                {
                    "ClassName1FirstPeriod": "Active Games (days 1-2)", 
                    "ClassName2FirstPeriod": "Improv (days 3-4)", 
                    "ItemNumber": 1, 
                    "Leader": "Jacquie Adain", 
                    "Leader2": "Howard Moody"
                }
            ], 
            "MorningFirstPeriod_Minimum": 0, 
            "MorningSecondPeriod": [
                {
                    "ClassName1SecondPeriod": "Folk Dancing", 
                    "ClassName2SecondPeriod": null, 
                    "ItemNumber": 1, 
                    "Leader": "Patricia Williams", 
                    "Leader2": ""
                }
            ], 
            "MorningSecondPeriod_Minimum": 0
        }, 
        "Fees": {
            "Age": null, 
            "Deposit": null, 
            "Deposit_Description": null, 
            "Deposit_Name": "Deposit", 
            "HousingLocation": "West Wing", 
            "Membership": "Member", 
            "Membership_Amount": null, 
            "Membership_Price": null, 
            "NumberInRoom": "2", 
            "PreferredRoommate2": "Robin Pierce", 
            "RemarksForRegistrar": null, 
            "RoomAndBoard": 580.0, 
            "RoomAndBoard_Description": null, 
            "RoomAndBoard_Name": "Room and Board", 
            "ScholarshipCode": null, 
            "Tuition": 200.0, 
            "Tuition_Description": "Tuition", 
            "Tuition_Name": "Tuition", 
            "Under18": false
        }, 
        "FoodPreference": "No preference", 
        "Gender": "Male", 
        "ItemNumber": 1, 
        "Name": {
            "First": "Dan", 
            "FirstAndLast": "Dan Rubin", 
            "Last": "Rubin", 
            "Middle": null, 
            "MiddleInitial": null, 
            "Prefix": null, 
            "Suffix": null
        }, 
        "Phone": "(516) 849-2987", 
        "Timestamp": 1508006302.0
    }, 
    {
        "ClassRegistration": {
            "AfternoonPeriod": [
                {
                    "ClassName1ThirdPeriod": "Corning Glass Adventure", 
                    "ClassName2ThirdPeriod": null, 
                    "ItemNumber": 1, 
                    "Leader": "Donna Miller-Small", 
                    "Leader2": ""
                }
            ], 
            "AfternoonPeriod_Minimum": 0, 
            "MorningFirstPeriod": [
                {
                    "ClassName1FirstPeriod": "Active Games (days 1-2)", 
                    "ClassName2FirstPeriod": "Improv (days 3-4)", 
                    "ItemNumber": 1, 
                    "Leader": "Jacquie Adain", 
                    "Leader2": "Howard Moody"
                }
            ], 
            "MorningFirstPeriod_Minimum": 0, 
            "MorningSecondPeriod": [
                {
                    "ClassName1SecondPeriod": "Folk Dancing", 
                    "ClassName2SecondPeriod": null, 
                    "ItemNumber": 1, 
                    "Leader": "Patricia Williams", 
                    "Leader2": ""
                }
            ], 
            "MorningSecondPeriod_Minimum": 0
        }, 
        "Fees": {
            "Age": null, 
            "Deposit": null, 
            "Deposit_Description": null, 
            "Deposit_Name": "Deposit", 
            "HousingLocation": "West Wing", 
            "Membership": "Newcomer", 
            "Membership_Amount": -50.0, 
            "Membership_Price": -50.0, 
            "NumberInRoom": "2", 
            "PreferredRoommate2": "Dan Rubin", 
            "RemarksForRegistrar": null, 
            "RoomAndBoard": 580.0, 
            "RoomAndBoard_Description": null, 
            "RoomAndBoard_Name": "Room and Board", 
            "ScholarshipCode": null, 
            "Tuition": 0.0, 
            "Tuition_Description": "Tuition", 
            "Tuition_Name": "Tuition", 
            "Under18": false
        }, 
        "FoodPreference": "No preference", 
        "Gender": "Female", 
        "ItemNumber": 2, 
        "Name": {
            "First": "Robin", 
            "FirstAndLast": "Robin Pierce", 
            "Last": "Pierce", 
            "Middle": null, 
            "MiddleInitial": null, 
            "Prefix": null, 
            "Suffix": null
        }, 
        "Phone": "(516) 205-4343", 
        "Timestamp": 1508006302.0
    }, 
    {
        "ClassRegistration": {
            "AfternoonPeriod": [
                {
                    "ClassName1ThirdPeriod": "Puppet Making (days 1-2)", 
                    "ClassName2ThirdPeriod": "Stepping into Desire", 
                    "ItemNumber": 1, 
                    "Leader": "Mickey Reed", 
                    "Leader2": "Betsy Reinstein"
                }
            ], 
            "AfternoonPeriod_Minimum": 0, 
            "MorningFirstPeriod": [
                {
                    "ClassName1FirstPeriod": "Active Games (days 1-2)", 
                    "ClassName2FirstPeriod": "Improv (days 3-4)", 
                    "ItemNumber": 1, 
                    "Leader": "Jacquie Adain", 
                    "Leader2": "Howard Moody"
                }
            ], 
            "MorningFirstPeriod_Minimum": 0, 
            "MorningSecondPeriod": [
                {
                    "ClassName1SecondPeriod": "Small Scenes", 
                    "ClassName2SecondPeriod": null, 
                    "ItemNumber": 1, 
                    "Leader": "Frank Baskin", 
                    "Leader2": ""
                }
            ], 
            "MorningSecondPeriod_Minimum": 0
        }, 
        "Fees": {
            "Age": null, 
            "Deposit": null, 
            "Deposit_Description": null, 
            "Deposit_Name": "Deposit", 
            "HousingLocation": "West Wing", 
            "Membership": "Non-Member", 
            "Membership_Amount": null, 
            "Membership_Price": null, 
            "NumberInRoom": "1", 
            "PreferredRoommate2": null, 
            "RemarksForRegistrar": null, 
            "RoomAndBoard": 0.0, 
            "RoomAndBoard_Description": null, 
            "RoomAndBoard_Name": "Room and Board", 
            "ScholarshipCode": "ECRSleader724", 
            "Tuition": 0.0, 
            "Tuition_Description": "Tuition", 
            "Tuition_Name": "Tuition", 
            "Under18": false
        }, 
        "FoodPreference": "No preference", 
        "Gender": "Female", 
        "ItemNumber": 3, 
        "Name": {
            "First": "Cassie", 
            "FirstAndLast": "Cassie Rubin", 
            "Last": "Rubin", 
            "Middle": null, 
            "MiddleInitial": null, 
            "Prefix": null, 
            "Suffix": null
        }, 
        "Phone": "(650) 520-3599", 
        "Timestamp": 1508006302.0
    }
]