[
    {
        "ClassRegistration": {
            "AfternoonPeriod": [
                {
                    "ClassName1ThirdPeriod": "Puppet Making (days 1-2)", 
                    "ClassName2ThirdPeriod": "Puppet Making (days 3-4)", 
                    "ItemNumber": 1, 
                    "Leader": "Mickey Reed", 
                    "Leader2": "Mickey Reed"
                }
            ], 
            "AfternoonPeriod_Minimum": 0, 
            "MorningFirstPeriod": [
                {
                    "ClassName1FirstPeriod": "Spoon Carving: Discovering What's Hidden Within", 
                    "ClassName2FirstPeriod": null, 
                    "ItemNumber": 1, 
                    "Leader": "Stephen Kaye", 
                    "Leader2": ""
                }
            ], 
            "MorningFirstPeriod_Minimum": 0, 
            "MorningSecondPeriod": [
                {
                    "ClassName1SecondPeriod": "Small Scenes", 
                    "ClassName2SecondPeriod": null, 
                    "ItemNumber": 1, 
                    "Leader": "Frank Baskin", 
                    "Leader2": ""
                }
            ], 
            "MorningSecondPeriod_Minimum": 0
        }, 
        "Fees": {
            "Age": null, 
            "Deposit": null, 
            "Deposit_Description": null, 
            "Deposit_Name": "Deposit", 
            "HousingLocation": "Main Lodge", 
            "Membership": "Member", 
            "Membership_Amount": null, 
            "Membership_Price": null, 
            "NumberInRoom": "2", 
            "PreferredRoommate2": "Frank Baskin", 
            "RemarksForRegistrar": null, 
            "RoomAndBoard": 335.0, 
            "RoomAndBoard_Description": null, 
            "RoomAndBoard_Name": "Room and Board", 
            "ScholarshipCode": null, 
            "Tuition": 200.0, 
            "Tuition_Description": "Tuition", 
            "Tuition_Name": "Tuition", 
            "Under18": false
        }, 
        "FoodPreference": "Vegetarian", 
        "Gender": "Female", 
        "ItemNumber": 1, 
        "Name": {
            "First": "Leslie", 
            "FirstAndLast": "Leslie Baskin", 
            "Last": "Baskin", 
            "Middle": null, 
            "MiddleInitial": null, 
            "Prefix": null, 
            "Suffix": null
        }, 
        "Phone": "(978) 458-1512", 
        "Timestamp": 1510689345.0
    }
]